django_anemie/__init__.py
django_anemie/apps.py
django_anemie/urls.py
django_anemie/views.py
django_anemie/static/django_anemie/css/style.css
django_anemie/templates/django_anemie/sensibilisation.html
django_anemie-0.1.0.dist-info/licenses/LICENSE
django_anemie-0.1.0.dist-info/METADATA
django_anemie-0.1.0.dist-info/WHEEL
django_anemie-0.1.0.dist-info/top_level.txt
django_anemie-0.1.0.dist-info/RECORD
